{"doc_id": "20011114/21.16.57-11242", "mpqa_sentence_level_annotations": [{"sentence_id": 0, "sentence_text": "United Nations, November 14 (XINHUA) -- It was unrealistic to envisage that people who were suffering from lack of development, poverty, hunger and poor health could fully enjoy their human rights, several delegations stressed Wednesday to the Third Committee (Social, Humanitarian, Cultural) of the 56th UN General Assembly.", "tokens_list": ["United", "Nations", ",", "November", "14", "(", "XINHUA", ")", "--", "It", "was", "unrealistic", "to", "envisage", "that", "people", "who", "were", "suffering", "from", "lack", "of", "development", ",", "poverty", ",", "hunger", "and", "poor", "health", "could", "fully", "enjoy", "their", "human", "rights", ",", "several", "delegations", "stressed", "Wednesday", "to", "the", "Third", "Committee", "(", "Social", ",", "Humanitarian", ",", "Cultural", ")", "of", "the", "56th", "UN", "General", "Assembly", "."], "role_mentions": [{"id": "20011114/21.16.57-11242_w,dels,implicit,people", "role_type": "HOLDER", "text": ["people"], "start": 15, "end": 16}, {"id": "20011114/21.16.57-11242_e9041", "role_type": "eTARGET", "start": 20, "end": 21, "text": ["lack"]}, {"id": "20011114/21.16.57-11242_e9043", "role_type": "eTARGET", "start": 24, "end": 25, "text": ["poverty"]}, {"id": "20011114/21.16.57-11242_e9044", "role_type": "eTARGET", "start": 26, "end": 27, "text": ["hunger"]}, {"id": "20011114/21.16.57-11242_e9045", "role_type": "eTARGET", "start": 29, "end": 30, "text": ["health"]}, {"id": "20011114/21.16.57-11242_w,dels", "role_type": "HOLDER", "text": ["several", "delegations"], "start": 37, "end": 39}, {"id": "20011114/21.16.57-11242_e9037", "role_type": "eTARGET", "start": 13, "end": 14, "text": ["envisage"]}], "opinion_mentions": [{"id": "20011114/21.16.57-11242_ds7_w,dels,implicit,people_e9041", "polarity": "negative", "trigger": {"text": "were suffering", "start": 17, "end": 19}, "arguments": [{"id": "20011114/21.16.57-11242_w,dels,implicit,people", "role_type": "HOLDER", "text": ["people"], "start": 15, "end": 16}, {"id": "20011114/21.16.57-11242_e9041", "role_type": "eTARGET", "start": 20, "end": 21, "text": ["lack"]}]}, {"id": "20011114/21.16.57-11242_ds7_w,dels,implicit,people_e9043", "polarity": "negative", "trigger": {"text": "were suffering", "start": 17, "end": 19}, "arguments": [{"id": "20011114/21.16.57-11242_w,dels,implicit,people", "role_type": "HOLDER", "text": ["people"], "start": 15, "end": 16}, {"id": "20011114/21.16.57-11242_e9043", "role_type": "eTARGET", "start": 24, "end": 25, "text": ["poverty"]}]}, {"id": "20011114/21.16.57-11242_ds7_w,dels,implicit,people_e9044", "polarity": "negative", "trigger": {"text": "were suffering", "start": 17, "end": 19}, "arguments": [{"id": "20011114/21.16.57-11242_w,dels,implicit,people", "role_type": "HOLDER", "text": ["people"], "start": 15, "end": 16}, {"id": "20011114/21.16.57-11242_e9044", "role_type": "eTARGET", "start": 26, "end": 27, "text": ["hunger"]}]}, {"id": "20011114/21.16.57-11242_ds7_w,dels,implicit,people_e9045", "polarity": "negative", "trigger": {"text": "were suffering", "start": 17, "end": 19}, "arguments": [{"id": "20011114/21.16.57-11242_w,dels,implicit,people", "role_type": "HOLDER", "text": ["people"], "start": 15, "end": 16}, {"id": "20011114/21.16.57-11242_e9045", "role_type": "eTARGET", "start": 29, "end": 30, "text": ["health"]}]}, {"id": "20011114/21.16.57-11242_ese15_w,dels_e9037", "polarity": "negative", "trigger": {"text": "unrealistic", "start": 11, "end": 12}, "arguments": [{"id": "20011114/21.16.57-11242_w,dels", "role_type": "HOLDER", "text": ["several", "delegations"], "start": 37, "end": 39}, {"id": "20011114/21.16.57-11242_e9037", "role_type": "eTARGET", "start": 13, "end": 14, "text": ["envisage"]}]}]}, {"sentence_id": 1, "sentence_text": "The committee Wednesday opened a formal debate on human rights questions, including alternative approaches for improving the effective enjoyment of human rights and fundamental freedoms.", "tokens_list": ["The", "committee", "Wednesday", "opened", "a", "formal", "debate", "on", "human", "rights", "questions", ",", "including", "alternative", "approaches", "for", "improving", "the", "effective", "enjoyment", "of", "human", "rights", "and", "fundamental", "freedoms", "."], "role_mentions": [], "opinion_mentions": []}, {"sentence_id": 2, "sentence_text": "Representatives said that the right to development was one of two major preconditions to ensure the universal protection and promotion of human rights, a press release of the committee said.", "tokens_list": ["Representatives", "said", "that", "the", "right", "to", "development", "was", "one", "of", "two", "major", "preconditions", "to", "ensure", "the", "universal", "protection", "and", "promotion", "of", "human", "rights", ",", "a", "press", "release", "of", "the", "committee", "said", "."], "role_mentions": [], "opinion_mentions": []}, {"sentence_id": 3, "sentence_text": "\"The second crucial element, maintaining international peace and security, was also emphasized as the Committee continued its debate on human rights questions, including alternative approaches for improving the effective enjoyment of human rights and fundamental freedoms,\" it said.", "tokens_list": ["\"", "The", "second", "crucial", "element", ",", "maintaining", "international", "peace", "and", "security", ",", "was", "also", "emphasized", "as", "the", "Committee", "continued", "its", "debate", "on", "human", "rights", "questions", ",", "including", "alternative", "approaches", "for", "improving", "the", "effective", "enjoyment", "of", "human", "rights", "and", "fundamental", "freedoms", ",", "\"", "it", "said", "."], "role_mentions": [], "opinion_mentions": []}, {"sentence_id": 4, "sentence_text": "Briefing on the remarks by the representative of Thailand, it said: \"Human rights and development were two sides of the same coin, and should be addressed in tandem.\"", "tokens_list": ["Briefing", "on", "the", "remarks", "by", "the", "representative", "of", "Thailand", ",", "it", "said", ":", "\"", "Human", "rights", "and", "development", "were", "two", "sides", "of", "the", "same", "coin", ",", "and", "should", "be", "addressed", "in", "tandem", ".", "\""], "role_mentions": [], "opinion_mentions": []}, {"sentence_id": 5, "sentence_text": "\"People should be at the center of social and economic development efforts.", "tokens_list": ["\"", "People", "should", "be", "at", "the", "center", "of", "social", "and", "economic", "development", "efforts", "."], "role_mentions": [], "opinion_mentions": []}, {"sentence_id": 6, "sentence_text": "They had to be protected from other scourges and social ills, including disease, narcotic drugs, armed conflicts, terrorism and other types of transnational organized crime,\" it added.", "tokens_list": ["They", "had", "to", "be", "protected", "from", "other", "scourges", "and", "social", "ills", ",", "including", "disease", ",", "narcotic", "drugs", ",", "armed", "conflicts", ",", "terrorism", "and", "other", "types", "of", "transnational", "organized", "crime", ",", "\"", "it", "added", "."], "role_mentions": [{"id": "20011114/21.16.57-11242_w,com", "role_type": "HOLDER", "text": ["it"], "start": 31, "end": 32}, {"id": "20011114/21.16.57-11242_e9010", "role_type": "eTARGET", "start": 7, "end": 8, "text": ["scourges"]}, {"id": "20011114/21.16.57-11242_e9011", "role_type": "eTARGET", "start": 10, "end": 11, "text": ["ills"]}], "opinion_mentions": [{"id": "20011114/21.16.57-11242_ese6_w,com_e9010", "polarity": "negative", "trigger": {"text": "scourges and social ills", "start": 7, "end": 11}, "arguments": [{"id": "20011114/21.16.57-11242_w,com", "role_type": "HOLDER", "text": ["it"], "start": 31, "end": 32}, {"id": "20011114/21.16.57-11242_e9010", "role_type": "eTARGET", "start": 7, "end": 8, "text": ["scourges"]}]}, {"id": "20011114/21.16.57-11242_ese6_w,com_e9011", "polarity": "negative", "trigger": {"text": "scourges and social ills", "start": 7, "end": 11}, "arguments": [{"id": "20011114/21.16.57-11242_w,com", "role_type": "HOLDER", "text": ["it"], "start": 31, "end": 32}, {"id": "20011114/21.16.57-11242_e9011", "role_type": "eTARGET", "start": 10, "end": 11, "text": ["ills"]}]}]}, {"sentence_id": 7, "sentence_text": "The representative of Eritrea said globalization was not only threatening to further marginalize the developing world and alienate its masses, it was also hampering the ability to exercise the rights and duties enshrined in numerous international human rights instruments, including the right to development.", "tokens_list": ["The", "representative", "of", "Eritrea", "said", "globalization", "was", "not", "only", "threatening", "to", "further", "marginalize", "the", "developing", "world", "and", "alienate", "its", "masses", ",", "it", "was", "also", "hampering", "the", "ability", "to", "exercise", "the", "rights", "and", "duties", "enshrined", "in", "numerous", "international", "human", "rights", "instruments", ",", "including", "the", "right", "to", "development", "."], "role_mentions": [{"id": "20011114/21.16.57-11242_w,erirep", "role_type": "HOLDER", "text": ["The", "representative", "of", "Eritrea"], "start": 0, "end": 4}, {"id": "20011114/21.16.57-11242_e9067", "role_type": "eTARGET", "start": 12, "end": 13, "text": ["marginalize"]}, {"id": "20011114/21.16.57-11242_e9070", "role_type": "eTARGET", "start": 17, "end": 18, "text": ["alienate"]}, {"id": "20011114/21.16.57-11242_e9072", "role_type": "eTARGET", "start": 21, "end": 22, "text": ["it"]}, {"id": "20011114/21.16.57-11242_e5001", "role_type": "eTARGET", "start": 9, "end": 10, "text": ["threatening"]}, {"id": "20011114/21.16.57-11242_e9065", "role_type": "eTARGET", "start": 5, "end": 6, "text": ["globalization"]}, {"id": "20011114/21.16.57-11242_e9074", "role_type": "eTARGET", "start": 24, "end": 25, "text": ["hampering"]}], "opinion_mentions": [{"id": "20011114/21.16.57-11242_ds2_w,erirep_e9067", "polarity": "negative", "trigger": {"text": "said", "start": 4, "end": 5}, "arguments": [{"id": "20011114/21.16.57-11242_w,erirep", "role_type": "HOLDER", "text": ["The", "representative", "of", "Eritrea"], "start": 0, "end": 4}, {"id": "20011114/21.16.57-11242_e9067", "role_type": "eTARGET", "start": 12, "end": 13, "text": ["marginalize"]}]}, {"id": "20011114/21.16.57-11242_ds2_w,erirep_e9070", "polarity": "negative", "trigger": {"text": "said", "start": 4, "end": 5}, "arguments": [{"id": "20011114/21.16.57-11242_w,erirep", "role_type": "HOLDER", "text": ["The", "representative", "of", "Eritrea"], "start": 0, "end": 4}, {"id": "20011114/21.16.57-11242_e9070", "role_type": "eTARGET", "start": 17, "end": 18, "text": ["alienate"]}]}, {"id": "20011114/21.16.57-11242_ds2_w,erirep_e9072", "polarity": "negative", "trigger": {"text": "said", "start": 4, "end": 5}, "arguments": [{"id": "20011114/21.16.57-11242_w,erirep", "role_type": "HOLDER", "text": ["The", "representative", "of", "Eritrea"], "start": 0, "end": 4}, {"id": "20011114/21.16.57-11242_e9072", "role_type": "eTARGET", "start": 21, "end": 22, "text": ["it"]}]}, {"id": "20011114/21.16.57-11242_ds2_w,erirep_e5001", "polarity": "negative", "trigger": {"text": "said", "start": 4, "end": 5}, "arguments": [{"id": "20011114/21.16.57-11242_w,erirep", "role_type": "HOLDER", "text": ["The", "representative", "of", "Eritrea"], "start": 0, "end": 4}, {"id": "20011114/21.16.57-11242_e5001", "role_type": "eTARGET", "start": 9, "end": 10, "text": ["threatening"]}]}, {"id": "20011114/21.16.57-11242_ds2_w,erirep_e9065", "polarity": "negative", "trigger": {"text": "said", "start": 4, "end": 5}, "arguments": [{"id": "20011114/21.16.57-11242_w,erirep", "role_type": "HOLDER", "text": ["The", "representative", "of", "Eritrea"], "start": 0, "end": 4}, {"id": "20011114/21.16.57-11242_e9065", "role_type": "eTARGET", "start": 5, "end": 6, "text": ["globalization"]}]}, {"id": "20011114/21.16.57-11242_ds2_w,erirep_e9074", "polarity": "negative", "trigger": {"text": "said", "start": 4, "end": 5}, "arguments": [{"id": "20011114/21.16.57-11242_w,erirep", "role_type": "HOLDER", "text": ["The", "representative", "of", "Eritrea"], "start": 0, "end": 4}, {"id": "20011114/21.16.57-11242_e9074", "role_type": "eTARGET", "start": 24, "end": 25, "text": ["hampering"]}]}]}, {"sentence_id": 8, "sentence_text": "\"Narrowing the development gap between countries was crucial to the realization of universal human rights,\" said the representative of China Shen Guofang.", "tokens_list": ["\"", "Narrowing", "the", "development", "gap", "between", "countries", "was", "crucial", "to", "the", "realization", "of", "universal", "human", "rights", ",", "\"", "said", "the", "representative", "of", "China", "Shen", "Guofang", "."], "role_mentions": [], "opinion_mentions": []}, {"sentence_id": 9, "sentence_text": "\"Underdevelopment had seriously hindered the capacity of developing countries to protect and promote human rights.\"", "tokens_list": ["\"", "Underdevelopment", "had", "seriously", "hindered", "the", "capacity", "of", "developing", "countries", "to", "protect", "and", "promote", "human", "rights", ".", "\""], "role_mentions": [], "opinion_mentions": []}, {"sentence_id": 10, "sentence_text": "\"With the rapid spread of globalization and economic expansion, the situation for poor countries was deteriorating with each passing day,\" Shen said.", "tokens_list": ["\"", "With", "the", "rapid", "spread", "of", "globalization", "and", "economic", "expansion", ",", "the", "situation", "for", "poor", "countries", "was", "deteriorating", "with", "each", "passing", "day", ",", "\"", "Shen", "said", "."], "role_mentions": [{"id": "20011114/21.16.57-11242_w,chinarep", "role_type": "HOLDER", "text": ["Shen"], "start": 24, "end": 25}, {"id": "20011114/21.16.57-11242_e9093", "role_type": "eTARGET", "start": 17, "end": 18, "text": ["deteriorating"]}], "opinion_mentions": [{"id": "20011114/21.16.57-11242_ds1_w,chinarep_e9093", "polarity": "negative", "trigger": {"text": "said", "start": 25, "end": 26}, "arguments": [{"id": "20011114/21.16.57-11242_w,chinarep", "role_type": "HOLDER", "text": ["Shen"], "start": 24, "end": 25}, {"id": "20011114/21.16.57-11242_e9093", "role_type": "eTARGET", "start": 17, "end": 18, "text": ["deteriorating"]}]}]}, {"sentence_id": 11, "sentence_text": "The representative of the United States said that despite the horrors of the terrorist attack, the international community could not truly win the war against terrorism unless human rights were protected.", "tokens_list": ["The", "representative", "of", "the", "United", "States", "said", "that", "despite", "the", "horrors", "of", "the", "terrorist", "attack", ",", "the", "international", "community", "could", "not", "truly", "win", "the", "war", "against", "terrorism", "unless", "human", "rights", "were", "protected", "."], "role_mentions": [{"id": "20011114/21.16.57-11242_w,usrep", "role_type": "HOLDER", "text": ["The", "representative", "of", "the", "United", "States"], "start": 0, "end": 6}, {"id": "20011114/21.16.57-11242_e9050", "role_type": "eTARGET", "start": 18, "end": 19, "text": ["community"]}, {"id": "20011114/21.16.57-11242_e9048", "role_type": "eTARGET", "start": 10, "end": 11, "text": ["horrors"]}, {"id": "20011114/21.16.57-11242_e9049", "role_type": "eTARGET", "start": 14, "end": 15, "text": ["attack"]}], "opinion_mentions": [{"id": "20011114/21.16.57-11242_ese8_w,usrep_e9050", "polarity": "negative", "trigger": {"text": "could not truly", "start": 19, "end": 22}, "arguments": [{"id": "20011114/21.16.57-11242_w,usrep", "role_type": "HOLDER", "text": ["The", "representative", "of", "the", "United", "States"], "start": 0, "end": 6}, {"id": "20011114/21.16.57-11242_e9050", "role_type": "eTARGET", "start": 18, "end": 19, "text": ["community"]}]}, {"id": "20011114/21.16.57-11242_ese14_w,usrep_e9048", "polarity": "negative", "trigger": {"text": "horrors of", "start": 10, "end": 12}, "arguments": [{"id": "20011114/21.16.57-11242_w,usrep", "role_type": "HOLDER", "text": ["The", "representative", "of", "the", "United", "States"], "start": 0, "end": 6}, {"id": "20011114/21.16.57-11242_e9048", "role_type": "eTARGET", "start": 10, "end": 11, "text": ["horrors"]}]}, {"id": "20011114/21.16.57-11242_ese14_w,usrep_e9049", "polarity": "negative", "trigger": {"text": "horrors of", "start": 10, "end": 12}, "arguments": [{"id": "20011114/21.16.57-11242_w,usrep", "role_type": "HOLDER", "text": ["The", "representative", "of", "the", "United", "States"], "start": 0, "end": 6}, {"id": "20011114/21.16.57-11242_e9049", "role_type": "eTARGET", "start": 14, "end": 15, "text": ["attack"]}]}]}, {"sentence_id": 12, "sentence_text": "\"There could be no expediency, no compromise, no lapse in vigilance,\" he said.", "tokens_list": ["\"", "There", "could", "be", "no", "expediency", ",", "no", "compromise", ",", "no", "lapse", "in", "vigilance", ",", "\"", "he", "said", "."], "role_mentions": [], "opinion_mentions": []}, {"sentence_id": 13, "sentence_text": "\"Promoting and strengthening human rights and democracy throughout the world was an integral part of the multilateral war on terrorism\".", "tokens_list": ["\"", "Promoting", "and", "strengthening", "human", "rights", "and", "democracy", "throughout", "the", "world", "was", "an", "integral", "part", "of", "the", "multilateral", "war", "on", "terrorism", "\"", "."], "role_mentions": [], "opinion_mentions": []}, {"sentence_id": 14, "sentence_text": "Also speaking on the debate were the representatives of Cuba, Egypt, Morocco, Japan, Venezuela, Mali, Greece and Indonesia.", "tokens_list": ["Also", "speaking", "on", "the", "debate", "were", "the", "representatives", "of", "Cuba", ",", "Egypt", ",", "Morocco", ",", "Japan", ",", "Venezuela", ",", "Mali", ",", "Greece", "and", "Indonesia", "."], "role_mentions": [], "opinion_mentions": []}, {"sentence_id": 15, "sentence_text": "The committee will meet again Thursday to continue its general debate on human rights questions.", "tokens_list": ["The", "committee", "will", "meet", "again", "Thursday", "to", "continue", "its", "general", "debate", "on", "human", "rights", "questions", "."], "role_mentions": [], "opinion_mentions": []}], "source": "MPQA_3.0", "num_sentences": 16, "sentences": [{"sentence_id": 0, "sentence_start": 0, "sentence_end": 326, "sentence_text": "United Nations, November 14 (XINHUA) -- It was unrealistic to envisage that people who were suffering from lack of development, poverty, hunger and poor health could fully enjoy their human rights, several delegations stressed Wednesday to the Third Committee (Social, Humanitarian, Cultural) of the 56th UN General Assembly.", "tokens_list": ["United", "Nations", ",", "November", "14", "(", "XINHUA", ")", "--", "It", "was", "unrealistic", "to", "envisage", "that", "people", "who", "were", "suffering", "from", "lack", "of", "development", ",", "poverty", ",", "hunger", "and", "poor", "health", "could", "fully", "enjoy", "their", "human", "rights", ",", "several", "delegations", "stressed", "Wednesday", "to", "the", "Third", "Committee", "(", "Social", ",", "Humanitarian", ",", "Cultural", ")", "of", "the", "56th", "UN", "General", "Assembly", "."], "tokens_dicts_list": [{"token": "United", "start_char": 0, "end_char": 6, "label": "non-event"}, {"token": "Nations", "start_char": 7, "end_char": 14, "label": "non-event"}, {"token": ",", "start_char": 14, "end_char": 15, "label": "non-event"}, {"token": "November", "start_char": 16, "end_char": 24, "label": "non-event"}, {"token": "14", "start_char": 25, "end_char": 27, "label": "non-event"}, {"token": "(", "start_char": 28, "end_char": 29, "label": "non-event"}, {"token": "XINHUA", "start_char": 29, "end_char": 35, "label": "non-event"}, {"token": ")", "start_char": 35, "end_char": 36, "label": "non-event"}, {"token": "--", "start_char": 37, "end_char": 39, "label": "non-event"}, {"token": "It", "start_char": 40, "end_char": 42, "label": "non-event"}, {"token": "was", "start_char": 43, "end_char": 46, "label": "non-event"}, {"token": "unrealistic", "start_char": 47, "end_char": 58, "label": "non-event"}, {"token": "to", "start_char": 59, "end_char": 61, "label": "non-event"}, {"token": "envisage", "start_char": 62, "end_char": 70, "label": "non-moral"}, {"token": "that", "start_char": 71, "end_char": 75, "label": "non-event"}, {"token": "people", "start_char": 76, "end_char": 82, "label": "non-event"}, {"token": "who", "start_char": 83, "end_char": 86, "label": "non-event"}, {"token": "were", "start_char": 87, "end_char": 91, "label": "non-event"}, {"token": "suffering", "start_char": 92, "end_char": 101, "label": "non-event"}, {"token": "from", "start_char": 102, "end_char": 106, "label": "non-event"}, {"token": "lack", "start_char": 107, "end_char": 111, "label": "non-moral"}, {"token": "of", "start_char": 112, "end_char": 114, "label": "non-event"}, {"token": "development", "start_char": 115, "end_char": 126, "label": "non-event"}, {"token": ",", "start_char": 126, "end_char": 127, "label": "non-event"}, {"token": "poverty", "start_char": 128, "end_char": 135, "label": "non-moral"}, {"token": ",", "start_char": 135, "end_char": 136, "label": "non-event"}, {"token": "hunger", "start_char": 137, "end_char": 143, "label": "non-moral"}, {"token": "and", "start_char": 144, "end_char": 147, "label": "non-event"}, {"token": "poor", "start_char": 148, "end_char": 152, "label": "non-moral"}, {"token": "health", "start_char": 153, "end_char": 159, "label": "non-event"}, {"token": "could", "start_char": 160, "end_char": 165, "label": "non-event"}, {"token": "fully", "start_char": 166, "end_char": 171, "label": "non-event"}, {"token": "enjoy", "start_char": 172, "end_char": 177, "label": "fairness"}, {"token": "their", "start_char": 178, "end_char": 183, "label": "non-event"}, {"token": "human", "start_char": 184, "end_char": 189, "label": "non-event"}, {"token": "rights", "start_char": 190, "end_char": 196, "label": "non-event"}, {"token": ",", "start_char": 196, "end_char": 197, "label": "non-event"}, {"token": "several", "start_char": 198, "end_char": 205, "label": "non-event"}, {"token": "delegations", "start_char": 206, "end_char": 217, "label": "non-event"}, {"token": "stressed", "start_char": 218, "end_char": 226, "label": "non-moral"}, {"token": "Wednesday", "start_char": 227, "end_char": 236, "label": "non-event"}, {"token": "to", "start_char": 237, "end_char": 239, "label": "non-event"}, {"token": "the", "start_char": 240, "end_char": 243, "label": "non-event"}, {"token": "Third", "start_char": 244, "end_char": 249, "label": "non-event"}, {"token": "Committee", "start_char": 250, "end_char": 259, "label": "non-moral"}, {"token": "(", "start_char": 260, "end_char": 261, "label": "non-event"}, {"token": "Social", "start_char": 261, "end_char": 267, "label": "non-event"}, {"token": ",", "start_char": 267, "end_char": 268, "label": "non-event"}, {"token": "Humanitarian", "start_char": 269, "end_char": 281, "label": "non-event"}, {"token": ",", "start_char": 281, "end_char": 282, "label": "non-event"}, {"token": "Cultural", "start_char": 283, "end_char": 291, "label": "non-event"}, {"token": ")", "start_char": 291, "end_char": 292, "label": "non-event"}, {"token": "of", "start_char": 293, "end_char": 295, "label": "non-event"}, {"token": "the", "start_char": 296, "end_char": 299, "label": "non-event"}, {"token": "56th", "start_char": 300, "end_char": 304, "label": "non-event"}, {"token": "UN", "start_char": 305, "end_char": 307, "label": "non-event"}, {"token": "General", "start_char": 308, "end_char": 315, "label": "non-event"}, {"token": "Assembly", "start_char": 316, "end_char": 324, "label": "non-event"}, {"token": ".", "start_char": 324, "end_char": 325, "label": "non-event"}], "tokens_label_list": ["non-event", "non-event", "non-event", "non-event", "non-event", "non-event", "non-event", "non-event", "non-event", "non-event", "non-event", "non-event", "non-event", "non-moral", "non-event", "non-event", "non-event", "non-event", "non-event", "non-event", "non-moral", "non-event", "non-event", "non-event", "non-moral", "non-event", "non-moral", "non-event", "non-moral", "non-event", "non-event", "non-event", "fairness", "non-event", "non-event", "non-event", "non-event", "non-event", "non-event", "non-moral", "non-event", "non-event", "non-event", "non-event", "non-moral", "non-event", "non-event", "non-event", "non-event", "non-event", "non-event", "non-event", "non-event", "non-event", "non-event", "non-event", "non-event", "non-event", "non-event"]}, {"sentence_id": 1, "sentence_start": 327, "sentence_end": 514, "sentence_text": "The committee Wednesday opened a formal debate on human rights questions, including alternative approaches for improving the effective enjoyment of human rights and fundamental freedoms.", "tokens_list": ["The", "committee", "Wednesday", "opened", "a", "formal", "debate", "on", "human", "rights", "questions", ",", "including", "alternative", "approaches", "for", "improving", "the", "effective", "enjoyment", "of", "human", "rights", "and", "fundamental", "freedoms", "."], "tokens_dicts_list": [{"token": "The", "start_char": 327, "end_char": 330, "label": "non-event"}, {"token": "committee", "start_char": 331, "end_char": 340, "label": "non-moral"}, {"token": "Wednesday", "start_char": 341, "end_char": 350, "label": "non-event"}, {"token": "opened", "start_char": 351, "end_char": 357, "label": "non-event"}, {"token": "a", "start_char": 358, "end_char": 359, "label": "non-event"}, {"token": "formal", "start_char": 360, "end_char": 366, "label": "non-event"}, {"token": "debate", "start_char": 367, "end_char": 373, "label": "non-moral"}, {"token": "on", "start_char": 374, "end_char": 376, "label": "non-event"}, {"token": "human", "start_char": 377, "end_char": 382, "label": "non-event"}, {"token": "rights", "start_char": 383, "end_char": 389, "label": "non-event"}, {"token": "questions", "start_char": 390, "end_char": 399, "label": "non-event"}, {"token": ",", "start_char": 399, "end_char": 400, "label": "non-event"}, {"token": "including", "start_char": 401, "end_char": 410, "label": "non-event"}, {"token": "alternative", "start_char": 411, "end_char": 422, "label": "non-event"}, {"token": "approaches", "start_char": 423, "end_char": 433, "label": "non-event"}, {"token": "for", "start_char": 434, "end_char": 437, "label": "non-event"}, {"token": "improving", "start_char": 438, "end_char": 447, "label": "fairness"}, {"token": "the", "start_char": 448, "end_char": 451, "label": "non-event"}, {"token": "effective", "start_char": 452, "end_char": 461, "label": "non-event"}, {"token": "enjoyment", "start_char": 462, "end_char": 471, "label": "fairness"}, {"token": "of", "start_char": 472, "end_char": 474, "label": "non-event"}, {"token": "human", "start_char": 475, "end_char": 480, "label": "non-event"}, {"token": "rights", "start_char": 481, "end_char": 487, "label": "non-event"}, {"token": "and", "start_char": 488, "end_char": 491, "label": "non-event"}, {"token": "fundamental", "start_char": 492, "end_char": 503, "label": "non-event"}, {"token": "freedoms", "start_char": 504, "end_char": 512, "label": "fairness"}, {"token": ".", "start_char": 512, "end_char": 513, "label": "non-event"}], "tokens_label_list": ["non-event", "non-moral", "non-event", "non-event", "non-event", "non-event", "non-moral", "non-event", "non-event", "non-event", "non-event", "non-event", "non-event", "non-event", "non-event", "non-event", "fairness", "non-event", "non-event", "fairness", "non-event", "non-event", "non-event", "non-event", "non-event", "fairness", "non-event"]}, {"sentence_id": 2, "sentence_start": 515, "sentence_end": 706, "sentence_text": "Representatives said that the right to development was one of two major preconditions to ensure the universal protection and promotion of human rights, a press release of the committee said.", "tokens_list": ["Representatives", "said", "that", "the", "right", "to", "development", "was", "one", "of", "two", "major", "preconditions", "to", "ensure", "the", "universal", "protection", "and", "promotion", "of", "human", "rights", ",", "a", "press", "release", "of", "the", "committee", "said", "."], "tokens_dicts_list": [{"token": "Representatives", "start_char": 515, "end_char": 530, "label": "non-event"}, {"token": "said", "start_char": 531, "end_char": 535, "label": "non-moral"}, {"token": "that", "start_char": 536, "end_char": 540, "label": "non-event"}, {"token": "the", "start_char": 541, "end_char": 544, "label": "non-event"}, {"token": "right", "start_char": 545, "end_char": 550, "label": "non-event"}, {"token": "to", "start_char": 551, "end_char": 553, "label": "non-event"}, {"token": "development", "start_char": 554, "end_char": 565, "label": "non-event"}, {"token": "was", "start_char": 566, "end_char": 569, "label": "non-event"}, {"token": "one", "start_char": 570, "end_char": 573, "label": "non-event"}, {"token": "of", "start_char": 574, "end_char": 576, "label": "non-event"}, {"token": "two", "start_char": 577, "end_char": 580, "label": "non-event"}, {"token": "major", "start_char": 581, "end_char": 586, "label": "non-event"}, {"token": "preconditions", "start_char": 587, "end_char": 600, "label": "non-event"}, {"token": "to", "start_char": 601, "end_char": 603, "label": "non-event"}, {"token": "ensure", "start_char": 604, "end_char": 610, "label": "fairness"}, {"token": "the", "start_char": 611, "end_char": 614, "label": "non-event"}, {"token": "universal", "start_char": 615, "end_char": 624, "label": "non-event"}, {"token": "protection", "start_char": 625, "end_char": 635, "label": "fairness"}, {"token": "and", "start_char": 636, "end_char": 639, "label": "non-event"}, {"token": "promotion", "start_char": 640, "end_char": 649, "label": "fairness"}, {"token": "of", "start_char": 650, "end_char": 652, "label": "non-event"}, {"token": "human", "start_char": 653, "end_char": 658, "label": "non-event"}, {"token": "rights", "start_char": 659, "end_char": 665, "label": "non-event"}, {"token": ",", "start_char": 665, "end_char": 666, "label": "non-event"}, {"token": "a", "start_char": 667, "end_char": 668, "label": "non-event"}, {"token": "press", "start_char": 669, "end_char": 674, "label": "non-event"}, {"token": "release", "start_char": 675, "end_char": 682, "label": "non-moral"}, {"token": "of", "start_char": 683, "end_char": 685, "label": "non-event"}, {"token": "the", "start_char": 686, "end_char": 689, "label": "non-event"}, {"token": "committee", "start_char": 690, "end_char": 699, "label": "non-moral"}, {"token": "said", "start_char": 700, "end_char": 704, "label": "non-moral"}, {"token": ".", "start_char": 704, "end_char": 705, "label": "non-event"}], "tokens_label_list": ["non-event", "non-moral", "non-event", "non-event", "non-event", "non-event", "non-event", "non-event", "non-event", "non-event", "non-event", "non-event", "non-event", "non-event", "fairness", "non-event", "non-event", "fairness", "non-event", "fairness", "non-event", "non-event", "non-event", "non-event", "non-event", "non-event", "non-moral", "non-event", "non-event", "non-moral", "non-moral", "non-event"]}, {"sentence_id": 3, "sentence_start": 707, "sentence_end": 990, "sentence_text": "\"The second crucial element, maintaining international peace and security, was also emphasized as the Committee continued its debate on human rights questions, including alternative approaches for improving the effective enjoyment of human rights and fundamental freedoms,\" it said.", "tokens_list": ["\"", "The", "second", "crucial", "element", ",", "maintaining", "international", "peace", "and", "security", ",", "was", "also", "emphasized", "as", "the", "Committee", "continued", "its", "debate", "on", "human", "rights", "questions", ",", "including", "alternative", "approaches", "for", "improving", "the", "effective", "enjoyment", "of", "human", "rights", "and", "fundamental", "freedoms", ",", "\"", "it", "said", "."], "tokens_dicts_list": [{"token": "\"", "start_char": 707, "end_char": 708, "label": "non-event"}, {"token": "The", "start_char": 708, "end_char": 711, "label": "non-event"}, {"token": "second", "start_char": 712, "end_char": 718, "label": "non-event"}, {"token": "crucial", "start_char": 719, "end_char": 726, "label": "non-event"}, {"token": "element", "start_char": 727, "end_char": 734, "label": "non-event"}, {"token": ",", "start_char": 734, "end_char": 735, "label": "non-event"}, {"token": "maintaining", "start_char": 736, "end_char": 747, "label": "non-event"}, {"token": "international", "start_char": 748, "end_char": 761, "label": "non-event"}, {"token": "peace", "start_char": 762, "end_char": 767, "label": "authority"}, {"token": "and", "start_char": 768, "end_char": 771, "label": "non-event"}, {"token": "security", "start_char": 772, "end_char": 780, "label": "authority"}, {"token": ",", "start_char": 780, "end_char": 781, "label": "non-event"}, {"token": "was", "start_char": 782, "end_char": 785, "label": "non-event"}, {"token": "also", "start_char": 786, "end_char": 790, "label": "non-event"}, {"token": "emphasized", "start_char": 791, "end_char": 801, "label": "non-moral"}, {"token": "as", "start_char": 802, "end_char": 804, "label": "non-event"}, {"token": "the", "start_char": 805, "end_char": 808, "label": "non-event"}, {"token": "Committee", "start_char": 809, "end_char": 818, "label": "non-moral"}, {"token": "continued", "start_char": 819, "end_char": 828, "label": "non-event"}, {"token": "its", "start_char": 829, "end_char": 832, "label": "non-event"}, {"token": "debate", "start_char": 833, "end_char": 839, "label": "non-moral"}, {"token": "on", "start_char": 840, "end_char": 842, "label": "non-event"}, {"token": "human", "start_char": 843, "end_char": 848, "label": "non-event"}, {"token": "rights", "start_char": 849, "end_char": 855, "label": "non-event"}, {"token": "questions", "start_char": 856, "end_char": 865, "label": "non-event"}, {"token": ",", "start_char": 865, "end_char": 866, "label": "non-event"}, {"token": "including", "start_char": 867, "end_char": 876, "label": "non-event"}, {"token": "alternative", "start_char": 877, "end_char": 888, "label": "non-event"}, {"token": "approaches", "start_char": 889, "end_char": 899, "label": "non-event"}, {"token": "for", "start_char": 900, "end_char": 903, "label": "non-event"}, {"token": "improving", "start_char": 904, "end_char": 913, "label": "fairness"}, {"token": "the", "start_char": 914, "end_char": 917, "label": "non-event"}, {"token": "effective", "start_char": 918, "end_char": 927, "label": "non-event"}, {"token": "enjoyment", "start_char": 928, "end_char": 937, "label": "fairness"}, {"token": "of", "start_char": 938, "end_char": 940, "label": "non-event"}, {"token": "human", "start_char": 941, "end_char": 946, "label": "non-event"}, {"token": "rights", "start_char": 947, "end_char": 953, "label": "non-event"}, {"token": "and", "start_char": 954, "end_char": 957, "label": "non-event"}, {"token": "fundamental", "start_char": 958, "end_char": 969, "label": "non-event"}, {"token": "freedoms", "start_char": 970, "end_char": 978, "label": "fairness"}, {"token": ",", "start_char": 978, "end_char": 979, "label": "non-event"}, {"token": "\"", "start_char": 979, "end_char": 980, "label": "non-event"}, {"token": "it", "start_char": 981, "end_char": 983, "label": "non-event"}, {"token": "said", "start_char": 984, "end_char": 988, "label": "non-moral"}, {"token": ".", "start_char": 988, "end_char": 989, "label": "non-event"}], "tokens_label_list": ["non-event", "non-event", "non-event", "non-event", "non-event", "non-event", "non-event", "non-event", "authority", "non-event", "authority", "non-event", "non-event", "non-event", "non-moral", "non-event", "non-event", "non-moral", "non-event", "non-event", "non-moral", "non-event", "non-event", "non-event", "non-event", "non-event", "non-event", "non-event", "non-event", "non-event", "fairness", "non-event", "non-event", "fairness", "non-event", "non-event", "non-event", "non-event", "non-event", "fairness", "non-event", "non-event", "non-event", "non-moral", "non-event"]}, {"sentence_id": 4, "sentence_start": 991, "sentence_end": 1158, "sentence_text": "Briefing on the remarks by the representative of Thailand, it said: \"Human rights and development were two sides of the same coin, and should be addressed in tandem.\"", "tokens_list": ["Briefing", "on", "the", "remarks", "by", "the", "representative", "of", "Thailand", ",", "it", "said", ":", "\"", "Human", "rights", "and", "development", "were", "two", "sides", "of", "the", "same", "coin", ",", "and", "should", "be", "addressed", "in", "tandem", ".", "\""], "tokens_dicts_list": [{"token": "Briefing", "start_char": 991, "end_char": 999, "label": "non-moral"}, {"token": "on", "start_char": 1000, "end_char": 1002, "label": "non-event"}, {"token": "the", "start_char": 1003, "end_char": 1006, "label": "non-event"}, {"token": "remarks", "start_char": 1007, "end_char": 1014, "label": "non-moral"}, {"token": "by", "start_char": 1015, "end_char": 1017, "label": "non-event"}, {"token": "the", "start_char": 1018, "end_char": 1021, "label": "non-event"}, {"token": "representative", "start_char": 1022, "end_char": 1036, "label": "non-event"}, {"token": "of", "start_char": 1037, "end_char": 1039, "label": "non-event"}, {"token": "Thailand", "start_char": 1040, "end_char": 1048, "label": "non-event"}, {"token": ",", "start_char": 1048, "end_char": 1049, "label": "non-event"}, {"token": "it", "start_char": 1050, "end_char": 1052, "label": "non-event"}, {"token": "said", "start_char": 1053, "end_char": 1057, "label": "non-moral"}, {"token": ":", "start_char": 1057, "end_char": 1058, "label": "non-event"}, {"token": "\"", "start_char": 1059, "end_char": 1060, "label": "non-event"}, {"token": "Human", "start_char": 1060, "end_char": 1065, "label": "non-event"}, {"token": "rights", "start_char": 1066, "end_char": 1072, "label": "fairness"}, {"token": "and", "start_char": 1073, "end_char": 1076, "label": "non-event"}, {"token": "development", "start_char": 1077, "end_char": 1088, "label": "non-moral"}, {"token": "were", "start_char": 1089, "end_char": 1093, "label": "non-event"}, {"token": "two", "start_char": 1094, "end_char": 1097, "label": "non-event"}, {"token": "sides", "start_char": 1098, "end_char": 1103, "label": "non-event"}, {"token": "of", "start_char": 1104, "end_char": 1106, "label": "non-event"}, {"token": "the", "start_char": 1107, "end_char": 1110, "label": "non-event"}, {"token": "same", "start_char": 1111, "end_char": 1115, "label": "non-event"}, {"token": "coin", "start_char": 1116, "end_char": 1120, "label": "non-event"}, {"token": ",", "start_char": 1120, "end_char": 1121, "label": "non-event"}, {"token": "and", "start_char": 1122, "end_char": 1125, "label": "non-event"}, {"token": "should", "start_char": 1126, "end_char": 1132, "label": "non-event"}, {"token": "be", "start_char": 1133, "end_char": 1135, "label": "non-event"}, {"token": "addressed", "start_char": 1136, "end_char": 1145, "label": "authority"}, {"token": "in", "start_char": 1146, "end_char": 1148, "label": "non-event"}, {"token": "tandem", "start_char": 1149, "end_char": 1155, "label": "non-event"}, {"token": ".", "start_char": 1155, "end_char": 1156, "label": "non-event"}, {"token": "\"", "start_char": 1156, "end_char": 1157, "label": "non-event"}], "tokens_label_list": ["non-moral", "non-event", "non-event", "non-moral", "non-event", "non-event", "non-event", "non-event", "non-event", "non-event", "non-event", "non-moral", "non-event", "non-event", "non-event", "fairness", "non-event", "non-moral", "non-event", "non-event", "non-event", "non-event", "non-event", "non-event", "non-event", "non-event", "non-event", "non-event", "non-event", "authority", "non-event", "non-event", "non-event", "non-event"]}, {"sentence_id": 5, "sentence_start": 1159, "sentence_end": 1235, "sentence_text": "\"People should be at the center of social and economic development efforts.", "tokens_list": ["\"", "People", "should", "be", "at", "the", "center", "of", "social", "and", "economic", "development", "efforts", "."], "tokens_dicts_list": [{"token": "\"", "start_char": 1159, "end_char": 1160, "label": "non-event"}, {"token": "People", "start_char": 1160, "end_char": 1166, "label": "non-event"}, {"token": "should", "start_char": 1167, "end_char": 1173, "label": "non-event"}, {"token": "be", "start_char": 1174, "end_char": 1176, "label": "non-event"}, {"token": "at", "start_char": 1177, "end_char": 1179, "label": "non-event"}, {"token": "the", "start_char": 1180, "end_char": 1183, "label": "non-event"}, {"token": "center", "start_char": 1184, "end_char": 1190, "label": "non-event"}, {"token": "of", "start_char": 1191, "end_char": 1193, "label": "non-event"}, {"token": "social", "start_char": 1194, "end_char": 1200, "label": "non-moral"}, {"token": "and", "start_char": 1201, "end_char": 1204, "label": "non-event"}, {"token": "economic", "start_char": 1205, "end_char": 1213, "label": "non-moral"}, {"token": "development", "start_char": 1214, "end_char": 1225, "label": "non-event"}, {"token": "efforts", "start_char": 1226, "end_char": 1233, "label": "non-event"}, {"token": ".", "start_char": 1233, "end_char": 1234, "label": "non-event"}], "tokens_label_list": ["non-event", "non-event", "non-event", "non-event", "non-event", "non-event", "non-event", "non-event", "non-moral", "non-event", "non-moral", "non-event", "non-event", "non-event"]}, {"sentence_id": 6, "sentence_start": 1235, "sentence_end": 1420, "sentence_text": "They had to be protected from other scourges and social ills, including disease, narcotic drugs, armed conflicts, terrorism and other types of transnational organized crime,\" it added.", "tokens_list": ["They", "had", "to", "be", "protected", "from", "other", "scourges", "and", "social", "ills", ",", "including", "disease", ",", "narcotic", "drugs", ",", "armed", "conflicts", ",", "terrorism", "and", "other", "types", "of", "transnational", "organized", "crime", ",", "\"", "it", "added", "."], "tokens_dicts_list": [{"token": "They", "start_char": 1235, "end_char": 1239, "label": "non-event"}, {"token": "had", "start_char": 1240, "end_char": 1243, "label": "non-event"}, {"token": "to", "start_char": 1244, "end_char": 1246, "label": "non-event"}, {"token": "be", "start_char": 1247, "end_char": 1249, "label": "non-event"}, {"token": "protected", "start_char": 1250, "end_char": 1259, "label": "care"}, {"token": "from", "start_char": 1260, "end_char": 1264, "label": "non-event"}, {"token": "other", "start_char": 1265, "end_char": 1270, "label": "non-event"}, {"token": "scourges", "start_char": 1271, "end_char": 1279, "label": "non-moral"}, {"token": "and", "start_char": 1280, "end_char": 1283, "label": "non-event"}, {"token": "social", "start_char": 1284, "end_char": 1290, "label": "non-event"}, {"token": "ills", "start_char": 1291, "end_char": 1295, "label": "non-moral"}, {"token": ",", "start_char": 1295, "end_char": 1296, "label": "non-event"}, {"token": "including", "start_char": 1297, "end_char": 1306, "label": "non-event"}, {"token": "disease", "start_char": 1307, "end_char": 1314, "label": "non-moral"}, {"token": ",", "start_char": 1314, "end_char": 1315, "label": "non-event"}, {"token": "narcotic", "start_char": 1316, "end_char": 1324, "label": "non-moral"}, {"token": "drugs", "start_char": 1325, "end_char": 1330, "label": "non-event"}, {"token": ",", "start_char": 1330, "end_char": 1331, "label": "non-event"}, {"token": "armed", "start_char": 1332, "end_char": 1337, "label": "non-event"}, {"token": "conflicts", "start_char": 1338, "end_char": 1347, "label": "harm"}, {"token": ",", "start_char": 1347, "end_char": 1348, "label": "non-event"}, {"token": "terrorism", "start_char": 1349, "end_char": 1358, "label": "subversion"}, {"token": "and", "start_char": 1359, "end_char": 1362, "label": "non-event"}, {"token": "other", "start_char": 1363, "end_char": 1368, "label": "non-event"}, {"token": "types", "start_char": 1369, "end_char": 1374, "label": "non-event"}, {"token": "of", "start_char": 1375, "end_char": 1377, "label": "non-event"}, {"token": "transnational", "start_char": 1378, "end_char": 1391, "label": "non-event"}, {"token": "organized", "start_char": 1392, "end_char": 1401, "label": "non-event"}, {"token": "crime", "start_char": 1402, "end_char": 1407, "label": "cheating"}, {"token": ",", "start_char": 1407, "end_char": 1408, "label": "non-event"}, {"token": "\"", "start_char": 1408, "end_char": 1409, "label": "non-event"}, {"token": "it", "start_char": 1410, "end_char": 1412, "label": "non-event"}, {"token": "added", "start_char": 1413, "end_char": 1418, "label": "non-moral"}, {"token": ".", "start_char": 1418, "end_char": 1419, "label": "non-event"}], "tokens_label_list": ["non-event", "non-event", "non-event", "non-event", "care", "non-event", "non-event", "non-moral", "non-event", "non-event", "non-moral", "non-event", "non-event", "non-moral", "non-event", "non-moral", "non-event", "non-event", "non-event", "harm", "non-event", "subversion", "non-event", "non-event", "non-event", "non-event", "non-event", "non-event", "cheating", "non-event", "non-event", "non-event", "non-moral", "non-event"]}, {"sentence_id": 7, "sentence_start": 1421, "sentence_end": 1730, "sentence_text": "The representative of Eritrea said globalization was not only threatening to further marginalize the developing world and alienate its masses, it was also hampering the ability to exercise the rights and duties enshrined in numerous international human rights instruments, including the right to development.", "tokens_list": ["The", "representative", "of", "Eritrea", "said", "globalization", "was", "not", "only", "threatening", "to", "further", "marginalize", "the", "developing", "world", "and", "alienate", "its", "masses", ",", "it", "was", "also", "hampering", "the", "ability", "to", "exercise", "the", "rights", "and", "duties", "enshrined", "in", "numerous", "international", "human", "rights", "instruments", ",", "including", "the", "right", "to", "development", "."], "tokens_dicts_list": [{"token": "The", "start_char": 1421, "end_char": 1424, "label": "non-event"}, {"token": "representative", "start_char": 1425, "end_char": 1439, "label": "non-event"}, {"token": "of", "start_char": 1440, "end_char": 1442, "label": "non-event"}, {"token": "Eritrea", "start_char": 1443, "end_char": 1450, "label": "non-event"}, {"token": "said", "start_char": 1451, "end_char": 1455, "label": "non-moral"}, {"token": "globalization", "start_char": 1456, "end_char": 1469, "label": "non-event"}, {"token": "was", "start_char": 1470, "end_char": 1473, "label": "non-event"}, {"token": "not", "start_char": 1474, "end_char": 1477, "label": "non-event"}, {"token": "only", "start_char": 1478, "end_char": 1482, "label": "non-event"}, {"token": "threatening", "start_char": 1483, "end_char": 1494, "label": "harm"}, {"token": "to", "start_char": 1495, "end_char": 1497, "label": "non-event"}, {"token": "further", "start_char": 1498, "end_char": 1505, "label": "non-event"}, {"token": "marginalize", "start_char": 1506, "end_char": 1517, "label": "cheating"}, {"token": "the", "start_char": 1518, "end_char": 1521, "label": "non-event"}, {"token": "developing", "start_char": 1522, "end_char": 1532, "label": "non-event"}, {"token": "world", "start_char": 1533, "end_char": 1538, "label": "non-event"}, {"token": "and", "start_char": 1539, "end_char": 1542, "label": "non-event"}, {"token": "alienate", "start_char": 1543, "end_char": 1551, "label": "cheating"}, {"token": "its", "start_char": 1552, "end_char": 1555, "label": "non-event"}, {"token": "masses", "start_char": 1556, "end_char": 1562, "label": "non-event"}, {"token": ",", "start_char": 1562, "end_char": 1563, "label": "non-event"}, {"token": "it", "start_char": 1564, "end_char": 1566, "label": "non-event"}, {"token": "was", "start_char": 1567, "end_char": 1570, "label": "non-event"}, {"token": "also", "start_char": 1571, "end_char": 1575, "label": "non-event"}, {"token": "hampering", "start_char": 1576, "end_char": 1585, "label": "subversion"}, {"token": "the", "start_char": 1586, "end_char": 1589, "label": "non-event"}, {"token": "ability", "start_char": 1590, "end_char": 1597, "label": "non-event"}, {"token": "to", "start_char": 1598, "end_char": 1600, "label": "non-event"}, {"token": "exercise", "start_char": 1601, "end_char": 1609, "label": "non-event"}, {"token": "the", "start_char": 1610, "end_char": 1613, "label": "non-event"}, {"token": "rights", "start_char": 1614, "end_char": 1620, "label": "fairness"}, {"token": "and", "start_char": 1621, "end_char": 1624, "label": "non-event"}, {"token": "duties", "start_char": 1625, "end_char": 1631, "label": "authority"}, {"token": "enshrined", "start_char": 1632, "end_char": 1641, "label": "non-moral"}, {"token": "in", "start_char": 1642, "end_char": 1644, "label": "non-event"}, {"token": "numerous", "start_char": 1645, "end_char": 1653, "label": "non-event"}, {"token": "international", "start_char": 1654, "end_char": 1667, "label": "non-event"}, {"token": "human", "start_char": 1668, "end_char": 1673, "label": "non-event"}, {"token": "rights", "start_char": 1674, "end_char": 1680, "label": "non-event"}, {"token": "instruments", "start_char": 1681, "end_char": 1692, "label": "non-event"}, {"token": ",", "start_char": 1692, "end_char": 1693, "label": "non-event"}, {"token": "including", "start_char": 1694, "end_char": 1703, "label": "non-event"}, {"token": "the", "start_char": 1704, "end_char": 1707, "label": "non-event"}, {"token": "right", "start_char": 1708, "end_char": 1713, "label": "non-event"}, {"token": "to", "start_char": 1714, "end_char": 1716, "label": "non-event"}, {"token": "development", "start_char": 1717, "end_char": 1728, "label": "non-event"}, {"token": ".", "start_char": 1728, "end_char": 1729, "label": "non-event"}], "tokens_label_list": ["non-event", "non-event", "non-event", "non-event", "non-moral", "non-event", "non-event", "non-event", "non-event", "harm", "non-event", "non-event", "cheating", "non-event", "non-event", "non-event", "non-event", "cheating", "non-event", "non-event", "non-event", "non-event", "non-event", "non-event", "subversion", "non-event", "non-event", "non-event", "non-event", "non-event", "fairness", "non-event", "authority", "non-moral", "non-event", "non-event", "non-event", "non-event", "non-event", "non-event", "non-event", "non-event", "non-event", "non-event", "non-event", "non-event", "non-event"]}, {"sentence_id": 8, "sentence_start": 1731, "sentence_end": 1886, "sentence_text": "\"Narrowing the development gap between countries was crucial to the realization of universal human rights,\" said the representative of China Shen Guofang.", "tokens_list": ["\"", "Narrowing", "the", "development", "gap", "between", "countries", "was", "crucial", "to", "the", "realization", "of", "universal", "human", "rights", ",", "\"", "said", "the", "representative", "of", "China", "Shen", "Guofang", "."], "tokens_dicts_list": [{"token": "\"", "start_char": 1731, "end_char": 1732, "label": "non-event"}, {"token": "Narrowing", "start_char": 1732, "end_char": 1741, "label": "authority"}, {"token": "the", "start_char": 1742, "end_char": 1745, "label": "non-event"}, {"token": "development", "start_char": 1746, "end_char": 1757, "label": "non-event"}, {"token": "gap", "start_char": 1758, "end_char": 1761, "label": "non-event"}, {"token": "between", "start_char": 1762, "end_char": 1769, "label": "non-event"}, {"token": "countries", "start_char": 1770, "end_char": 1779, "label": "non-event"}, {"token": "was", "start_char": 1780, "end_char": 1783, "label": "non-event"}, {"token": "crucial", "start_char": 1784, "end_char": 1791, "label": "non-event"}, {"token": "to", "start_char": 1792, "end_char": 1794, "label": "non-event"}, {"token": "the", "start_char": 1795, "end_char": 1798, "label": "non-event"}, {"token": "realization", "start_char": 1799, "end_char": 1810, "label": "fairness"}, {"token": "of", "start_char": 1811, "end_char": 1813, "label": "non-event"}, {"token": "universal", "start_char": 1814, "end_char": 1823, "label": "non-event"}, {"token": "human", "start_char": 1824, "end_char": 1829, "label": "non-event"}, {"token": "rights", "start_char": 1830, "end_char": 1836, "label": "non-event"}, {"token": ",", "start_char": 1836, "end_char": 1837, "label": "non-event"}, {"token": "\"", "start_char": 1837, "end_char": 1838, "label": "non-event"}, {"token": "said", "start_char": 1839, "end_char": 1843, "label": "non-moral"}, {"token": "the", "start_char": 1844, "end_char": 1847, "label": "non-event"}, {"token": "representative", "start_char": 1848, "end_char": 1862, "label": "non-event"}, {"token": "of", "start_char": 1863, "end_char": 1865, "label": "non-event"}, {"token": "China", "start_char": 1866, "end_char": 1871, "label": "non-event"}, {"token": "Shen", "start_char": 1872, "end_char": 1876, "label": "non-event"}, {"token": "Guofang", "start_char": 1877, "end_char": 1884, "label": "non-event"}, {"token": ".", "start_char": 1884, "end_char": 1885, "label": "non-event"}], "tokens_label_list": ["non-event", "authority", "non-event", "non-event", "non-event", "non-event", "non-event", "non-event", "non-event", "non-event", "non-event", "fairness", "non-event", "non-event", "non-event", "non-event", "non-event", "non-event", "non-moral", "non-event", "non-event", "non-event", "non-event", "non-event", "non-event", "non-event"]}, {"sentence_id": 9, "sentence_start": 1886, "sentence_end": 2002, "sentence_text": "\"Underdevelopment had seriously hindered the capacity of developing countries to protect and promote human rights.\"", "tokens_list": ["\"", "Underdevelopment", "had", "seriously", "hindered", "the", "capacity", "of", "developing", "countries", "to", "protect", "and", "promote", "human", "rights", ".", "\""], "tokens_dicts_list": [{"token": "\"", "start_char": 1886, "end_char": 1887, "label": "non-event"}, {"token": "Underdevelopment", "start_char": 1887, "end_char": 1903, "label": "non-event"}, {"token": "had", "start_char": 1904, "end_char": 1907, "label": "non-event"}, {"token": "seriously", "start_char": 1908, "end_char": 1917, "label": "non-event"}, {"token": "hindered", "start_char": 1918, "end_char": 1926, "label": "non-moral"}, {"token": "the", "start_char": 1927, "end_char": 1930, "label": "non-event"}, {"token": "capacity", "start_char": 1931, "end_char": 1939, "label": "non-event"}, {"token": "of", "start_char": 1940, "end_char": 1942, "label": "non-event"}, {"token": "developing", "start_char": 1943, "end_char": 1953, "label": "non-event"}, {"token": "countries", "start_char": 1954, "end_char": 1963, "label": "non-event"}, {"token": "to", "start_char": 1964, "end_char": 1966, "label": "non-event"}, {"token": "protect", "start_char": 1967, "end_char": 1974, "label": "fairness"}, {"token": "and", "start_char": 1975, "end_char": 1978, "label": "non-event"}, {"token": "promote", "start_char": 1979, "end_char": 1986, "label": "fairness"}, {"token": "human", "start_char": 1987, "end_char": 1992, "label": "non-event"}, {"token": "rights", "start_char": 1993, "end_char": 1999, "label": "non-event"}, {"token": ".", "start_char": 1999, "end_char": 2000, "label": "non-event"}, {"token": "\"", "start_char": 2000, "end_char": 2001, "label": "non-event"}], "tokens_label_list": ["non-event", "non-event", "non-event", "non-event", "non-moral", "non-event", "non-event", "non-event", "non-event", "non-event", "non-event", "fairness", "non-event", "fairness", "non-event", "non-event", "non-event", "non-event"]}, {"sentence_id": 10, "sentence_start": 2003, "sentence_end": 2153, "sentence_text": "\"With the rapid spread of globalization and economic expansion, the situation for poor countries was deteriorating with each passing day,\" Shen said.", "tokens_list": ["\"", "With", "the", "rapid", "spread", "of", "globalization", "and", "economic", "expansion", ",", "the", "situation", "for", "poor", "countries", "was", "deteriorating", "with", "each", "passing", "day", ",", "\"", "Shen", "said", "."], "tokens_dicts_list": [{"token": "\"", "start_char": 2003, "end_char": 2004, "label": "non-event"}, {"token": "With", "start_char": 2004, "end_char": 2008, "label": "non-event"}, {"token": "the", "start_char": 2009, "end_char": 2012, "label": "non-event"}, {"token": "rapid", "start_char": 2013, "end_char": 2018, "label": "non-event"}, {"token": "spread", "start_char": 2019, "end_char": 2025, "label": "non-event"}, {"token": "of", "start_char": 2026, "end_char": 2028, "label": "non-event"}, {"token": "globalization", "start_char": 2029, "end_char": 2042, "label": "non-moral"}, {"token": "and", "start_char": 2043, "end_char": 2046, "label": "non-event"}, {"token": "economic", "start_char": 2047, "end_char": 2055, "label": "non-event"}, {"token": "expansion", "start_char": 2056, "end_char": 2065, "label": "non-moral"}, {"token": ",", "start_char": 2065, "end_char": 2066, "label": "non-event"}, {"token": "the", "start_char": 2067, "end_char": 2070, "label": "non-event"}, {"token": "situation", "start_char": 2071, "end_char": 2080, "label": "non-event"}, {"token": "for", "start_char": 2081, "end_char": 2084, "label": "non-event"}, {"token": "poor", "start_char": 2085, "end_char": 2089, "label": "non-event"}, {"token": "countries", "start_char": 2090, "end_char": 2099, "label": "non-event"}, {"token": "was", "start_char": 2100, "end_char": 2103, "label": "non-event"}, {"token": "deteriorating", "start_char": 2104, "end_char": 2117, "label": "non-moral"}, {"token": "with", "start_char": 2118, "end_char": 2122, "label": "non-event"}, {"token": "each", "start_char": 2123, "end_char": 2127, "label": "non-event"}, {"token": "passing", "start_char": 2128, "end_char": 2135, "label": "non-event"}, {"token": "day", "start_char": 2136, "end_char": 2139, "label": "non-event"}, {"token": ",", "start_char": 2139, "end_char": 2140, "label": "non-event"}, {"token": "\"", "start_char": 2140, "end_char": 2141, "label": "non-event"}, {"token": "Shen", "start_char": 2142, "end_char": 2146, "label": "non-event"}, {"token": "said", "start_char": 2147, "end_char": 2151, "label": "non-moral"}, {"token": ".", "start_char": 2151, "end_char": 2152, "label": "non-event"}], "tokens_label_list": ["non-event", "non-event", "non-event", "non-event", "non-event", "non-event", "non-moral", "non-event", "non-event", "non-moral", "non-event", "non-event", "non-event", "non-event", "non-event", "non-event", "non-event", "non-moral", "non-event", "non-event", "non-event", "non-event", "non-event", "non-event", "non-event", "non-moral", "non-event"]}, {"sentence_id": 11, "sentence_start": 2154, "sentence_end": 2359, "sentence_text": "The representative of the United States said that despite the horrors of the terrorist attack, the international community could not truly win the war against terrorism unless human rights were protected.", "tokens_list": ["The", "representative", "of", "the", "United", "States", "said", "that", "despite", "the", "horrors", "of", "the", "terrorist", "attack", ",", "the", "international", "community", "could", "not", "truly", "win", "the", "war", "against", "terrorism", "unless", "human", "rights", "were", "protected", "."], "tokens_dicts_list": [{"token": "The", "start_char": 2154, "end_char": 2157, "label": "non-event"}, {"token": "representative", "start_char": 2158, "end_char": 2172, "label": "non-event"}, {"token": "of", "start_char": 2173, "end_char": 2175, "label": "non-event"}, {"token": "the", "start_char": 2176, "end_char": 2179, "label": "non-event"}, {"token": "United", "start_char": 2180, "end_char": 2186, "label": "non-event"}, {"token": "States", "start_char": 2187, "end_char": 2193, "label": "non-event"}, {"token": "said", "start_char": 2194, "end_char": 2198, "label": "non-moral"}, {"token": "that", "start_char": 2199, "end_char": 2203, "label": "non-event"}, {"token": "despite", "start_char": 2204, "end_char": 2211, "label": "non-event"}, {"token": "the", "start_char": 2212, "end_char": 2215, "label": "non-event"}, {"token": "horrors", "start_char": 2216, "end_char": 2223, "label": "non-event"}, {"token": "of", "start_char": 2224, "end_char": 2226, "label": "non-event"}, {"token": "the", "start_char": 2227, "end_char": 2230, "label": "non-event"}, {"token": "terrorist", "start_char": 2231, "end_char": 2240, "label": "non-event"}, {"token": "attack", "start_char": 2241, "end_char": 2247, "label": "subversion"}, {"token": ",", "start_char": 2247, "end_char": 2248, "label": "non-event"}, {"token": "the", "start_char": 2249, "end_char": 2252, "label": "non-event"}, {"token": "international", "start_char": 2253, "end_char": 2266, "label": "non-event"}, {"token": "community", "start_char": 2267, "end_char": 2276, "label": "non-event"}, {"token": "could", "start_char": 2277, "end_char": 2282, "label": "non-event"}, {"token": "not", "start_char": 2283, "end_char": 2286, "label": "non-event"}, {"token": "truly", "start_char": 2287, "end_char": 2292, "label": "non-event"}, {"token": "win", "start_char": 2293, "end_char": 2296, "label": "non-moral"}, {"token": "the", "start_char": 2297, "end_char": 2300, "label": "non-event"}, {"token": "war", "start_char": 2301, "end_char": 2304, "label": "non-moral"}, {"token": "against", "start_char": 2305, "end_char": 2312, "label": "non-event"}, {"token": "terrorism", "start_char": 2313, "end_char": 2322, "label": "subversion"}, {"token": "unless", "start_char": 2323, "end_char": 2329, "label": "non-event"}, {"token": "human", "start_char": 2330, "end_char": 2335, "label": "non-event"}, {"token": "rights", "start_char": 2336, "end_char": 2342, "label": "non-event"}, {"token": "were", "start_char": 2343, "end_char": 2347, "label": "non-event"}, {"token": "protected", "start_char": 2348, "end_char": 2357, "label": "fairness"}, {"token": ".", "start_char": 2357, "end_char": 2358, "label": "non-event"}], "tokens_label_list": ["non-event", "non-event", "non-event", "non-event", "non-event", "non-event", "non-moral", "non-event", "non-event", "non-event", "non-event", "non-event", "non-event", "non-event", "subversion", "non-event", "non-event", "non-event", "non-event", "non-event", "non-event", "non-event", "non-moral", "non-event", "non-moral", "non-event", "subversion", "non-event", "non-event", "non-event", "non-event", "fairness", "non-event"]}, {"sentence_id": 12, "sentence_start": 2360, "sentence_end": 2439, "sentence_text": "\"There could be no expediency, no compromise, no lapse in vigilance,\" he said.", "tokens_list": ["\"", "There", "could", "be", "no", "expediency", ",", "no", "compromise", ",", "no", "lapse", "in", "vigilance", ",", "\"", "he", "said", "."], "tokens_dicts_list": [{"token": "\"", "start_char": 2360, "end_char": 2361, "label": "non-event"}, {"token": "There", "start_char": 2361, "end_char": 2366, "label": "non-event"}, {"token": "could", "start_char": 2367, "end_char": 2372, "label": "non-event"}, {"token": "be", "start_char": 2373, "end_char": 2375, "label": "non-event"}, {"token": "no", "start_char": 2376, "end_char": 2378, "label": "non-event"}, {"token": "expediency", "start_char": 2379, "end_char": 2389, "label": "subversion"}, {"token": ",", "start_char": 2389, "end_char": 2390, "label": "non-event"}, {"token": "no", "start_char": 2391, "end_char": 2393, "label": "non-event"}, {"token": "compromise", "start_char": 2394, "end_char": 2404, "label": "subversion"}, {"token": ",", "start_char": 2404, "end_char": 2405, "label": "non-event"}, {"token": "no", "start_char": 2406, "end_char": 2408, "label": "non-event"}, {"token": "lapse", "start_char": 2409, "end_char": 2414, "label": "subversion"}, {"token": "in", "start_char": 2415, "end_char": 2417, "label": "non-event"}, {"token": "vigilance", "start_char": 2418, "end_char": 2427, "label": "non-event"}, {"token": ",", "start_char": 2427, "end_char": 2428, "label": "non-event"}, {"token": "\"", "start_char": 2428, "end_char": 2429, "label": "non-event"}, {"token": "he", "start_char": 2430, "end_char": 2432, "label": "non-event"}, {"token": "said", "start_char": 2433, "end_char": 2437, "label": "non-moral"}, {"token": ".", "start_char": 2437, "end_char": 2438, "label": "non-event"}], "tokens_label_list": ["non-event", "non-event", "non-event", "non-event", "non-event", "subversion", "non-event", "non-event", "subversion", "non-event", "non-event", "subversion", "non-event", "non-event", "non-event", "non-event", "non-event", "non-moral", "non-event"]}, {"sentence_id": 13, "sentence_start": 2439, "sentence_end": 2576, "sentence_text": "\"Promoting and strengthening human rights and democracy throughout the world was an integral part of the multilateral war on terrorism\".", "tokens_list": ["\"", "Promoting", "and", "strengthening", "human", "rights", "and", "democracy", "throughout", "the", "world", "was", "an", "integral", "part", "of", "the", "multilateral", "war", "on", "terrorism", "\"", "."], "tokens_dicts_list": [{"token": "\"", "start_char": 2439, "end_char": 2440, "label": "non-event"}, {"token": "Promoting", "start_char": 2440, "end_char": 2449, "label": "fairness"}, {"token": "and", "start_char": 2450, "end_char": 2453, "label": "non-event"}, {"token": "strengthening", "start_char": 2454, "end_char": 2467, "label": "fairness"}, {"token": "human", "start_char": 2468, "end_char": 2473, "label": "non-event"}, {"token": "rights", "start_char": 2474, "end_char": 2480, "label": "non-event"}, {"token": "and", "start_char": 2481, "end_char": 2484, "label": "non-event"}, {"token": "democracy", "start_char": 2485, "end_char": 2494, "label": "non-event"}, {"token": "throughout", "start_char": 2495, "end_char": 2505, "label": "non-event"}, {"token": "the", "start_char": 2506, "end_char": 2509, "label": "non-event"}, {"token": "world", "start_char": 2510, "end_char": 2515, "label": "non-event"}, {"token": "was", "start_char": 2516, "end_char": 2519, "label": "non-event"}, {"token": "an", "start_char": 2520, "end_char": 2522, "label": "non-event"}, {"token": "integral", "start_char": 2523, "end_char": 2531, "label": "non-event"}, {"token": "part", "start_char": 2532, "end_char": 2536, "label": "non-event"}, {"token": "of", "start_char": 2537, "end_char": 2539, "label": "non-event"}, {"token": "the", "start_char": 2540, "end_char": 2543, "label": "non-event"}, {"token": "multilateral", "start_char": 2544, "end_char": 2556, "label": "non-event"}, {"token": "war", "start_char": 2557, "end_char": 2560, "label": "non-moral"}, {"token": "on", "start_char": 2561, "end_char": 2563, "label": "non-event"}, {"token": "terrorism", "start_char": 2564, "end_char": 2573, "label": "subversion"}, {"token": "\"", "start_char": 2573, "end_char": 2574, "label": "non-event"}, {"token": ".", "start_char": 2574, "end_char": 2575, "label": "non-event"}], "tokens_label_list": ["non-event", "fairness", "non-event", "fairness", "non-event", "non-event", "non-event", "non-event", "non-event", "non-event", "non-event", "non-event", "non-event", "non-event", "non-event", "non-event", "non-event", "non-event", "non-moral", "non-event", "subversion", "non-event", "non-event"]}, {"sentence_id": 14, "sentence_start": 2577, "sentence_end": 2701, "sentence_text": "Also speaking on the debate were the representatives of Cuba, Egypt, Morocco, Japan, Venezuela, Mali, Greece and Indonesia.", "tokens_list": ["Also", "speaking", "on", "the", "debate", "were", "the", "representatives", "of", "Cuba", ",", "Egypt", ",", "Morocco", ",", "Japan", ",", "Venezuela", ",", "Mali", ",", "Greece", "and", "Indonesia", "."], "tokens_dicts_list": [{"token": "Also", "start_char": 2577, "end_char": 2581, "label": "non-event"}, {"token": "speaking", "start_char": 2582, "end_char": 2590, "label": "non-moral"}, {"token": "on", "start_char": 2591, "end_char": 2593, "label": "non-event"}, {"token": "the", "start_char": 2594, "end_char": 2597, "label": "non-event"}, {"token": "debate", "start_char": 2598, "end_char": 2604, "label": "non-moral"}, {"token": "were", "start_char": 2605, "end_char": 2609, "label": "non-event"}, {"token": "the", "start_char": 2610, "end_char": 2613, "label": "non-event"}, {"token": "representatives", "start_char": 2614, "end_char": 2629, "label": "non-event"}, {"token": "of", "start_char": 2630, "end_char": 2632, "label": "non-event"}, {"token": "Cuba", "start_char": 2633, "end_char": 2637, "label": "non-event"}, {"token": ",", "start_char": 2637, "end_char": 2638, "label": "non-event"}, {"token": "Egypt", "start_char": 2639, "end_char": 2644, "label": "non-event"}, {"token": ",", "start_char": 2644, "end_char": 2645, "label": "non-event"}, {"token": "Morocco", "start_char": 2646, "end_char": 2653, "label": "non-event"}, {"token": ",", "start_char": 2653, "end_char": 2654, "label": "non-event"}, {"token": "Japan", "start_char": 2655, "end_char": 2660, "label": "non-event"}, {"token": ",", "start_char": 2660, "end_char": 2661, "label": "non-event"}, {"token": "Venezuela", "start_char": 2662, "end_char": 2671, "label": "non-event"}, {"token": ",", "start_char": 2671, "end_char": 2672, "label": "non-event"}, {"token": "Mali", "start_char": 2673, "end_char": 2677, "label": "non-event"}, {"token": ",", "start_char": 2677, "end_char": 2678, "label": "non-event"}, {"token": "Greece", "start_char": 2679, "end_char": 2685, "label": "non-event"}, {"token": "and", "start_char": 2686, "end_char": 2689, "label": "non-event"}, {"token": "Indonesia", "start_char": 2690, "end_char": 2699, "label": "non-event"}, {"token": ".", "start_char": 2699, "end_char": 2700, "label": "non-event"}], "tokens_label_list": ["non-event", "non-moral", "non-event", "non-event", "non-moral", "non-event", "non-event", "non-event", "non-event", "non-event", "non-event", "non-event", "non-event", "non-event", "non-event", "non-event", "non-event", "non-event", "non-event", "non-event", "non-event", "non-event", "non-event", "non-event", "non-event"]}, {"sentence_id": 15, "sentence_start": 2702, "sentence_end": 2798, "sentence_text": "The committee will meet again Thursday to continue its general debate on human rights questions", "tokens_list": ["The", "committee", "will", "meet", "again", "Thursday", "to", "continue", "its", "general", "debate", "on", "human", "rights", "questions"], "tokens_dicts_list": [{"token": "The", "start_char": 2702, "end_char": 2705, "label": "non-event"}, {"token": "committee", "start_char": 2706, "end_char": 2715, "label": "non-moral"}, {"token": "will", "start_char": 2716, "end_char": 2720, "label": "non-event"}, {"token": "meet", "start_char": 2721, "end_char": 2725, "label": "non-moral"}, {"token": "again", "start_char": 2726, "end_char": 2731, "label": "non-event"}, {"token": "Thursday", "start_char": 2732, "end_char": 2740, "label": "non-event"}, {"token": "to", "start_char": 2741, "end_char": 2743, "label": "non-event"}, {"token": "continue", "start_char": 2744, "end_char": 2752, "label": "non-event"}, {"token": "its", "start_char": 2753, "end_char": 2756, "label": "non-event"}, {"token": "general", "start_char": 2757, "end_char": 2764, "label": "non-event"}, {"token": "debate", "start_char": 2765, "end_char": 2771, "label": "non-moral"}, {"token": "on", "start_char": 2772, "end_char": 2774, "label": "non-event"}, {"token": "human", "start_char": 2775, "end_char": 2780, "label": "non-event"}, {"token": "rights", "start_char": 2781, "end_char": 2787, "label": "non-event"}, {"token": "questions", "start_char": 2788, "end_char": 2797, "label": "non-moral"}], "tokens_label_list": ["non-event", "non-moral", "non-event", "non-moral", "non-event", "non-event", "non-event", "non-event", "non-event", "non-event", "non-moral", "non-event", "non-event", "non-event", "non-moral"]}]}